MANIFEST.in
README.md
setup.cfg
setup.py
tox.ini
blueflood_carbon_forwarder.egg-info/PKG-INFO
blueflood_carbon_forwarder.egg-info/SOURCES.txt
blueflood_carbon_forwarder.egg-info/dependency_links.txt
blueflood_carbon_forwarder.egg-info/requires.txt
blueflood_carbon_forwarder.egg-info/top_level.txt
bluefloodserver/__init__.py
bluefloodserver/__init__.pyc
bluefloodserver/blueflood.py
bluefloodserver/blueflood.pyc
bluefloodserver/collect.py
bluefloodserver/collect.pyc
bluefloodserver/protocols.py
bluefloodserver/protocols.pyc
bluefloodserver/util.py
bluefloodserver/util.pyc
carbonforwarderlogging/__init__.py
carbonforwarderlogging/forwarder_log_observer.py
tests/http_server_mock.py
tests/http_server_mock.pyc
tests/test_blueflood.py
tests/test_blueflood.pyc
tests/test_bluefloodserver.py
tests/test_bluefloodserver.pyc
tests/test_collect.py
tests/test_collect.pyc
tests/test_integration.py
tests/test_integration.pyc
tests/test_protocols.py
tests/test_protocols.pyc
tests/__pycache__/test_blueflood.cpython-27-PYTEST.pyc
tests/__pycache__/test_bluefloodserver.cpython-27-PYTEST.pyc
tests/__pycache__/test_collect.cpython-27-PYTEST.pyc
tests/__pycache__/test_integration.cpython-27-PYTEST.pyc
tests/__pycache__/test_protocols.cpython-27-PYTEST.pyc
tests/scripts/sendPickle.py
twisted/plugins/graphite_blueflood_plugin.py