Metadata-Version: 1.1
Name: blueflood-carbon-forwarder
Version: 0.4.1
Summary: Sending graphite metrics to blueflood
Home-page: https://github.com/rackerlabs/blueflood-carbon-forwarder
Author: Rackspace Metrics
Author-email: cloudMetrics-dev@lists.rackspace.com
License: Apache Software License
Platform: any
Classifier: Programming Language :: Python
Classifier: Development Status :: 4 - Beta
Classifier: Natural Language :: English
Classifier: Environment :: Web Environment
Classifier: Intended Audience :: Developers
Classifier: License :: OSI Approved :: Apache Software License
Classifier: Operating System :: OS Independent
Classifier: Topic :: Internet :: WWW/HTTP :: Dynamic Content
